README
setup.py
makeprogress.egg-info/PKG-INFO
makeprogress.egg-info/SOURCES.txt
makeprogress.egg-info/dependency_links.txt
makeprogress.egg-info/entry_points.txt
makeprogress.egg-info/requires.txt
makeprogress.egg-info/top_level.txt
progress/__init__.py
progress/example.py
progress/server.py
progress/progress/__init__.py
progress/progress/progress.py
progress/static/style.css
progress/templates/archive.html
progress/templates/default.html