Metadata-Version: 1.0
Name: makeprogress
Version: 0.0.3.1
Summary: Use progress to manage weekly snippets.
Home-page: https://github.com/csu/progress
Author: Christopher Su
Author-email: gh@christopher.su
License: UNKNOWN
Platform: UNKNOWN
